nonebot_plugin_alchelper-0.6.0.dist-info/METADATA
nonebot_plugin_alchelper-0.6.0.dist-info/WHEEL
nonebot_plugin_alchelper-0.6.0.dist-info/entry_points.txt
nonebot_plugin_alchelper-0.6.0.dist-info/licenses/LICENSE
nonebot_plugin_alchelper/__init__.py
nonebot_plugin_alchelper/config.py
nonebot_plugin_alchelper/migrations/7420f69398ee_0_6_0.py
nonebot_plugin_alchelper/migrations/a9a3810efa4a_0_5_0.py
nonebot_plugin_alchelper/model.py
nonebot_plugin_alchelper-0.6.0.dist-info/RECORD
