Metadata-Version: 2.1
Name: nonebot-plugin-alchelper
Version: 0.6.0
Summary: 以nonebot-plugin-alconna为基础提供系列帮助功能的插件
Author-Email: RF-Tar-Railt <rf_tar_railt@qq.com>
License: MIT
Requires-Python: >=3.9
Requires-Dist: nonebot2>=2.4.0
Requires-Dist: nonebot-plugin-alconna>=0.54.1
Requires-Dist: nonebot-plugin-orm>=0.7.6
Provides-Extra: default
Requires-Dist: sqlalchemy[aiosqlite]; extra == "default"
Provides-Extra: mysql
Requires-Dist: sqlalchemy[aiomysql]; extra == "mysql"
Provides-Extra: asyncmy
Requires-Dist: sqlalchemy[asyncmy]; extra == "asyncmy"
Provides-Extra: aiomysql
Requires-Dist: sqlalchemy[aiomysql]; extra == "aiomysql"
Provides-Extra: postgresql
Requires-Dist: sqlalchemy[postgresql_psycopgbinary]; extra == "postgresql"
Provides-Extra: psycopg
Requires-Dist: sqlalchemy[postgresql_psycopgbinary]; extra == "psycopg"
Provides-Extra: asyncpg
Requires-Dist: sqlalchemy[postgresql_asyncpg]; extra == "asyncpg"
Provides-Extra: sqlite
Requires-Dist: sqlalchemy[aiosqlite]; extra == "sqlite"
Provides-Extra: aiosqlite
Requires-Dist: sqlalchemy[aiosqlite]; extra == "aiosqlite"
